joker_minions-0.0-py3.7-nspkg.pth
joker/minions/__init__.py
joker/minions/bloom.py
joker/minions/cache.py
joker/minions/utils.py
joker_minions-0.0.dist-info/METADATA
joker_minions-0.0.dist-info/WHEEL
joker_minions-0.0.dist-info/namespace_packages.txt
joker_minions-0.0.dist-info/top_level.txt
joker_minions-0.0.dist-info/RECORD
